sayou/refinery/__init__.py
sayou/refinery/pipeline.py
sayou/refinery/core/exceptions.py
sayou/refinery/interfaces/base_normalizer.py
sayou/refinery/interfaces/base_processor.py
sayou/refinery/normalizer/doc_markdown_normalizer.py
sayou/refinery/normalizer/html_text_normalizer.py
sayou/refinery/normalizer/record_normalizer.py
sayou/refinery/plugins/link_processor.py
sayou/refinery/plugins/white_space_processor.py
sayou/refinery/processor/deduplicator.py
sayou/refinery/processor/imputer.py
sayou/refinery/processor/outlier_handler.py
sayou/refinery/processor/pii_masker.py
sayou/refinery/processor/text_cleaner.py
sayou_refinery-0.3.7.dist-info/METADATA
sayou_refinery-0.3.7.dist-info/WHEEL
sayou_refinery-0.3.7.dist-info/RECORD
